mwa_pb/__init__.py
mwa_pb/beam_full_EE.py
mwa_pb/beam_tools.py
mwa_pb/config.py
mwa_pb/make_beam.py
mwa_pb/measured_beamformer.py
mwa_pb/metadata.py
mwa_pb/mwa_impedance.py
mwa_pb/mwa_sweet_spots.py
mwa_pb/mwa_tile.py
mwa_pb/mwapb.py
mwa_pb/primary_beam.py
mwa_pb/primarybeammap.py
mwa_pb/primarybeammap_tant.py
mwa_pb/skyfield_utils.py
mwa_pb/skymap.py
mwa_pb/suppress.py
mwa_pb/data/G4Jy_catalogue_allEGCcolumns.fits
mwa_pb/data/HIP_constellations.dat
mwa_pb/data/Jmatrix.fits
mwa_pb/data/README.txt
mwa_pb/data/ZMatrix.fits
mwa_pb/data/constellationship.fab
mwa_pb/data/meas_delays.txt
mwa_pb/data/meas_gain_db.txt
mwa_pb/data/mwa_full_embedded_element_pattern.h5
mwa_pb/data/radio408.RaDec.fits
mwa_pb-1.1.data/scripts/beam_correct_image.py
mwa_pb-1.1.data/scripts/beamtest.py
mwa_pb-1.1.data/scripts/calc_jones.py
mwa_pb-1.1.data/scripts/make_beam_test.py
mwa_pb-1.1.data/scripts/mwa_sensitivity.py
mwa_pb-1.1.data/scripts/plot_skymap.py
mwa_pb-1.1.data/scripts/primarybeammap_tant_test.py
mwa_pb-1.1.data/scripts/track_and_suppress.py
mwa_pb-1.1.dist-info/LICENSE
mwa_pb-1.1.dist-info/METADATA
mwa_pb-1.1.dist-info/WHEEL
mwa_pb-1.1.dist-info/top_level.txt
mwa_pb-1.1.dist-info/RECORD
